{
  "$schema": "https://zed.dev/schema/themes/v0.2.0.json",
  "name": "Moleskine",
  "author": "mini Editor",
  "themes": [
    {
      "name": "Moleskine Light",
      "appearance": "light",
      "style": {
        "border": "#EFEAE1ff",
        "border.variant": "#E8DCC8ff",
        "border.focused": "#3484F7ff",
        "border.selected": "#E8DCC8ff",
        "border.transparent": "#00000000",
        "border.disabled": "#F5F0E7ff",
        "elevated_surface.background": "#FAF6EFff",
        "surface.background": "#FAF6EFff",
        "background": "#FAF6EFff",
        "element.background": "#F5F0E7ff",
        "element.hover": "#EBE3D6ff",
        "element.active": "#E8DCC8ff",
        "element.selected": "#E8DCC8ff",
        "element.disabled": "#F5F0E7ff",
        "drop_target.background": "#E8DCC8B3",
        "ghost_element.background": "#00000000",
        "ghost_element.hover": "#EBE3D6ff",
        "ghost_element.active": "#E8DCC8ff",
        "ghost_element.selected": "#E8DCC8ff",
        "ghost_element.disabled": "#F5F0E7ff",
        "text": "#2C2416ff",
        "text.muted": "#6B5E4Fff",
        "text.placeholder": "#8B7355ff",
        "text.disabled": "#8B7355ff",
        "text.accent": "#3484F7ff",
        "icon": "#2C2416ff",
        "icon.muted": "#6B5E4Fff",
        "icon.disabled": "#8B7355ff",
        "icon.placeholder": "#6B5E4Fff",
        "icon.accent": "#3484F7ff",
        "status_bar.background": "#FAF6EFff",
        "title_bar.background": "#FAF6EFff",
        "title_bar.inactive_background": "#F5F0E7ff",
        "toolbar.background": "#FAF6EFff",
        "tab_bar.background": "#F5F0E7ff",
        "tab.inactive_background": "#F5F0E7ff",
        "tab.active_background": "#FAF6EFff",
        "search.match_background": "#3484F766",
        "search.active_match_background": "#E8DCC8B3",
        "panel.background": "#FAF6EFff",
        "panel.focused_border": null,
        "pane.focused_border": null,
        "scrollbar.thumb.background": "#E8DCC84C",
        "scrollbar.thumb.hover_background": "#EBE3D6ff",
        "scrollbar.thumb.border": "#EFEAE1ff",
        "scrollbar.track.background": "#00000000",
        "scrollbar.track.border": "#EFEAE1ff",
        "editor.foreground": "#2C2416ff",
        "editor.background": "#FAF6EFff",
        "editor.gutter.background": "#FAF6EFff",
        "editor.subheader.background": "#F5F0E7ff",
        "editor.active_line.background": "#F5F0E710",
        "editor.highlighted_line.background": "#F5F0E7ff",
        "editor.line_number": "#8B7355",
        "editor.active_line_number": "#2C2416ff",
        "editor.hover_line_number": "#6B5E4Fff",
        "editor.invisible": "#E8DCC8ff",
        "editor.wrap_guide": "#EFEAE10D",
        "editor.active_wrap_guide": "#EFEAE11A",
        "editor.document_highlight.read_background": "#3484F71A",
        "editor.document_highlight.write_background": "#E8DCC866",
        "terminal.background": "#FAF6EFff",
        "terminal.foreground": "#2C2416ff",
        "terminal.bright_foreground": "#2C2416ff",
        "terminal.dim_foreground": "#6B5E4Fff",
        "terminal.ansi.black": "#2C2416ff",
        "terminal.ansi.bright_black": "#6B5E4Fff",
        "terminal.ansi.dim_black": "#8B7355ff",
        "terminal.ansi.red": "#D07277ff",
        "terminal.ansi.bright_red": "#8B4513ff",
        "terminal.ansi.dim_red": "#EAB7B9ff",
        "terminal.ansi.green": "#2E7D32ff",
        "terminal.ansi.bright_green": "#4d6140ff",
        "terminal.ansi.dim_green": "#A1C181ff",
        "terminal.ansi.yellow": "#DEC184ff",
        "terminal.ansi.bright_yellow": "#E5C07Bff",
        "terminal.ansi.dim_yellow": "#F1DFC1ff",
        "terminal.ansi.blue": "#3484F7ff",
        "terminal.ansi.bright_blue": "#1565C0ff",
        "terminal.ansi.dim_blue": "#BED5F4ff",
        "terminal.ansi.magenta": "#8B4513ff",
        "terminal.ansi.bright_magenta": "#B477CFff",
        "terminal.ansi.dim_magenta": "#612A79ff",
        "terminal.ansi.cyan": "#00695Cff",
        "terminal.ansi.bright_cyan": "#3A565Bff",
        "terminal.ansi.dim_cyan": "#6EB4BFff",
        "terminal.ansi.white": "#2C2416ff",
        "terminal.ansi.bright_white": "#FAF6EFff",
        "terminal.ansi.dim_white": "#6B5E4Fff",
        "link_text.hover": "#3484F7ff",
        "version_control.added": "#2E7D32ff",
        "version_control.modified": "#DEC184ff",
        "version_control.removed": "#D07277ff",
        "version_control.removed_highlight": "#D07277ff",
        "version_control.conflict": "#8B4513ff",
        "version_control.ignored": "#8B7355ff"
      },
      "syntax": {
        "comment": "#8B7355ff",
        "comment.doc": "#6B5E4Fff",
        "comment.line": "#8B7355ff",
        "comment.block": "#8B7355ff",
        "constant": "#1565C0ff",
        "constant.builtin": "#1565C0ff",
        "constant.character": "#2E7D32ff",
        "constant.character.escape": "#8B4513ff",
        "constant.numeric": "#1565C0ff",
        "constructor": "#00695Cff",
        "function": "#00695Cff",
        "function.builtin": "#00695Cff",
        "function.method": "#00695Cff",
        "function.macro": "#8B4513ff",
        "function.special": "#8B4513ff",
        "keyword": "#8B4513ff",
        "keyword.control": "#8B4513ff",
        "keyword.control.conditional": "#8B4513ff",
        "keyword.control.repeat": "#8B4513ff",
        "keyword.control.import": "#8B4513ff",
        "keyword.control.return": "#8B4513ff",
        "keyword.control.exception": "#8B4513ff",
        "keyword.function": "#8B4513ff",
        "keyword.operator": "#2C2416ff",
        "keyword.operator.new": "#8B4513ff",
        "keyword.other": "#8B4513ff",
        "keyword.storage": "#8B4513ff",
        "keyword.storage.type": "#8B4513ff",
        "keyword.storage.modifier": "#8B4513ff",
        "label": "#6A1B9Aff",
        "markup.bold": "#2C2416ff",
        "markup.heading": "#2C2416ff",
        "markup.heading.marker": "#6B5E4Fff",
        "markup.italic": "#6B5E4Fff",
        "markup.link": "#3484F7ff",
        "markup.link.text": "#3484F7ff",
        "markup.list": "#2C2416ff",
        "markup.list.numbered": "#2C2416ff",
        "markup.list.unnumbered": "#2C2416ff",
        "markup.quote": "#6B5E4Fff",
        "markup.raw": "#2E7D32ff",
        "markup.raw.block": "#2E7D32ff",
        "markup.raw.inline": "#2E7D32ff",
        "markup.strikethrough": "#8B7355ff",
        "markup.underline": "#3484F7ff",
        "namespace": "#6A1B9Aff",
        "operator": "#2C2416ff",
        "property": "#2C2416ff",
        "punctuation": "#2C2416ff",
        "punctuation.bracket": "#2C2416ff",
        "punctuation.delimiter": "#2C2416ff",
        "punctuation.special": "#2C2416ff",
        "string": "#2E7D32ff",
        "string.regexp": "#2E7D32ff",
        "string.special": "#2E7D32ff",
        "string.special.path": "#2E7D32ff",
        "string.special.symbol": "#2E7D32ff",
        "string.special.url": "#3484F7ff",
        "tag": "#00695Cff",
        "type": "#6A1B9Aff",
        "type.builtin": "#6A1B9Aff",
        "type.enum": "#6A1B9Aff",
        "type.enum.variant": "#00695Cff",
        "variable": "#2C2416ff",
        "variable.builtin": "#8B4513ff",
        "variable.function": "#00695Cff",
        "variable.member": "#2C2416ff",
        "variable.other": "#2C2416ff",
        "variable.parameter": "#2C2416ff"
      }
    }
  ]
}
